sudhirpakage/__init__.py
sudhirpakage/sudhir.py
sudhirpakage1-0.0.5.dist-info/LICENSE
sudhirpakage1-0.0.5.dist-info/METADATA
sudhirpakage1-0.0.5.dist-info/WHEEL
sudhirpakage1-0.0.5.dist-info/top_level.txt
sudhirpakage1-0.0.5.dist-info/RECORD
